{
	"configurations" : 
	[
		{
			"directories" : 
			[
				{
					"build" : ".",
					"childIndexes" : 
					[
						1,
						2
					],
					"jsonFile" : "directory-.-Debug-f5ebdc15457944623624.json",
					"minimumCMakeVersion" : 
					{
						"string" : "3.10"
					},
					"projectIndex" : 0,
					"source" : ".",
					"targetIndexes" : 
					[
						2
					]
				},
				{
					"build" : "function_matrix",
					"jsonFile" : "directory-function_matrix-Debug-7a9dc1a38a29d5582305.json",
					"minimumCMakeVersion" : 
					{
						"string" : "3.10"
					},
					"parentIndex" : 0,
					"projectIndex" : 1,
					"source" : "function_matrix",
					"targetIndexes" : 
					[
						1
					]
				},
				{
					"build" : "decision_CLY",
					"jsonFile" : "directory-decision_CLY-Debug-363fa8ef4c3a32df1388.json",
					"minimumCMakeVersion" : 
					{
						"string" : "3.10"
					},
					"parentIndex" : 0,
					"projectIndex" : 2,
					"source" : "decision_CLY",
					"targetIndexes" : 
					[
						0
					]
				}
			],
			"name" : "Debug",
			"projects" : 
			[
				{
					"childIndexes" : 
					[
						1,
						2
					],
					"directoryIndexes" : 
					[
						0
					],
					"name" : "matrix",
					"targetIndexes" : 
					[
						2
					]
				},
				{
					"directoryIndexes" : 
					[
						1
					],
					"name" : "function_matrix",
					"parentIndex" : 0,
					"targetIndexes" : 
					[
						1
					]
				},
				{
					"directoryIndexes" : 
					[
						2
					],
					"name" : "CLY",
					"parentIndex" : 0,
					"targetIndexes" : 
					[
						0
					]
				}
			],
			"targets" : 
			[
				{
					"directoryIndex" : 2,
					"id" : "decision_CLY::@82a1e42a4f38f017fa3f",
					"jsonFile" : "target-decision_CLY-Debug-b875d8bd5ce3117103db.json",
					"name" : "decision_CLY",
					"projectIndex" : 2
				},
				{
					"directoryIndex" : 1,
					"id" : "function_matrix::@170211f4f19f196d1b03",
					"jsonFile" : "target-function_matrix-Debug-64df83bd7161c220fc1e.json",
					"name" : "function_matrix",
					"projectIndex" : 1
				},
				{
					"directoryIndex" : 0,
					"id" : "main::@6890427a1f51a3e7e1df",
					"jsonFile" : "target-main-Debug-baddb0708b91d9783e75.json",
					"name" : "main",
					"projectIndex" : 0
				}
			]
		}
	],
	"kind" : "codemodel",
	"paths" : 
	{
		"build" : "/home/s23380409@unn.global/project/c++/matrix/build",
		"source" : "/home/s23380409@unn.global/project/c++/matrix"
	},
	"version" : 
	{
		"major" : 2,
		"minor" : 3
	}
}
